{"@context": "https://schema.org", "@type": "VideoGame", "name": "Transistor", "url": "https://www.3djuegos.com/15860/transistor/", "datePublished": "2014-05-20", "applicationCategory": "Game", "description": "Aventura de rol dise\u00f1ada por los creadores del exitoso Bastion, que apuestan por la ciencia ficci\u00f3n en este t\u00edtulo que combina la estrategia con ciertas secuencias de acci\u00f3n vertiginosa.", "publisher": ["Supergiant Games"], "gamePlatform": "PC", "operatingSystem": "PC Windows", "genre": ["Rol", "Acci\u00f3n RPG"], "aggregateRating": {"@type": "AggregateRating", "ratingValue": "8,6", "bestRating": 10, "worstRating": 0, "ratingCount": 136}, "image": "https://i11d.3djuegos.com/juegos/9753/transistor/fotos/ficha/transistor-2273347.jpg", "thumbnailUrl": "https://i11d.3djuegos.com/juegos/9753/transistor/fotos/ficha/transistor-2273347.jpg", "contentRating": "PG-12", "numberOfPlayers": 1, "author": {"@type": "Organization", "name": "Supergiant Games", "url": "http://www.supergiantgames.com/"}, "sameAs": "http://supergiantgames.com/index.php/transistor/"}